coercer/__init__.py
coercer/__main__.py
coercer/core/Filter.py
coercer/core/Reporter.py
coercer/core/__init__.py
coercer/core/loader.py
coercer/core/modes/__init__.py
coercer/core/modes/coerce.py
coercer/core/modes/fuzz.py
coercer/core/modes/scan.py
coercer/core/utils.py
coercer/methods/MS_DFSNM/NetrDfsAddStdRoot.py
coercer/methods/MS_DFSNM/NetrDfsRemoveStdRoot.py
coercer/methods/MS_DFSNM/__init__.py
coercer/methods/MS_EFSR/EfsRpcAddUsersToFile.py
coercer/methods/MS_EFSR/EfsRpcAddUsersToFileEx.py
coercer/methods/MS_EFSR/EfsRpcDecryptFileSrv.py
coercer/methods/MS_EFSR/EfsRpcDuplicateEncryptionInfoFile.py
coercer/methods/MS_EFSR/EfsRpcEncryptFileSrv.py
coercer/methods/MS_EFSR/EfsRpcFileKeyInfo.py
coercer/methods/MS_EFSR/EfsRpcOpenFileRaw.py
coercer/methods/MS_EFSR/EfsRpcQueryRecoveryAgents.py
coercer/methods/MS_EFSR/EfsRpcQueryUsersOnFile.py
coercer/methods/MS_EFSR/EfsRpcRemoveUsersFromFile.py
coercer/methods/MS_EFSR/__init__.py
coercer/methods/MS_EVEN/ElfrOpenBELW.py
coercer/methods/MS_EVEN/__init__.py
coercer/methods/MS_FSRVP/IsPathShadowCopied.py
coercer/methods/MS_FSRVP/IsPathSupported.py
coercer/methods/MS_FSRVP/__init__.py
coercer/methods/MS_RPRN/RpcRemoteFindFirstPrinterChangeNotification.py
coercer/methods/MS_RPRN/RpcRemoteFindFirstPrinterChangeNotificationEx.py
coercer/methods/MS_RPRN/__init__.py
coercer/methods/__init__.py
coercer/models/MSPROTOCOLRPCCALL.py
coercer/models/__init__.py
coercer/network/DCERPCSession.py
coercer/network/DCERPCSessionError.py
coercer/network/Listener.py
coercer/network/__init__.py
coercer/network/authentications.py
coercer/network/rpc.py
coercer/network/smb.py
coercer/network/utils.py
coercer/structures/Credentials.py
coercer/structures/MethodType.py
coercer/structures/ReportingLevel.py
coercer/structures/TestResult.py
coercer/structures/__init__.py
coercer-2.4.3.dist-info/METADATA
coercer-2.4.3.dist-info/WHEEL
coercer-2.4.3.dist-info/entry_points.txt
coercer-2.4.3.dist-info/RECORD
